visualize_algos/__init__.py
visualize_algos/path_finding_algos.py
visualize_algos/ui_based_path_search.py
visualize_alogs-0.0.1.dist-info/METADATA
visualize_alogs-0.0.1.dist-info/WHEEL
visualize_alogs-0.0.1.dist-info/top_level.txt
visualize_alogs-0.0.1.dist-info/RECORD
