Metadata-Version: 2.1
Name: visualize-alogs
Version: 0.0.1
Summary: Visualize path finding algorithms simultaneously for the same condition in UI.
Author: Dhvanik Viradiya
Author-email: viradiyadhvanik@gmail.com
Classifier: Programming Language :: Python :: 3
Classifier: Operating System :: OS Independent
Requires-Python: >=3.6
